biapack/__init__.py
biapack/basic_client.py
biapack/util.py
biapack/schema/__init__.py
biapack/schema/header.py
biapack-0.0.2.dist-info/METADATA
biapack-0.0.2.dist-info/WHEEL
biapack-0.0.2.dist-info/top_level.txt
biapack-0.0.2.dist-info/RECORD
