Metadata-Version: 2.4
Name: biapack
Version: 0.0.2
Summary: Biblioteca para desenvolvedores que utilizam o BiaAgentBuilder
Author-email: Bia Platform <data.platform@sankhya.com.br>
License: MIT
Requires-Python: >=3.10
